ottype/__init__.py
ottype/_version.py
ottype/core.py
ottype/core_boost.c
ottype/core_boost.cpython-312-x86_64-linux-gnu.so
ottype/core_boost.pyx
ottype/py.typed
python_ottype-25.7.0.dist-info/METADATA
python_ottype-25.7.0.dist-info/WHEEL
python_ottype-25.7.0.dist-info/top_level.txt
python_ottype-25.7.0.dist-info/RECORD
python_ottype-25.7.0.dist-info/licenses/LICENSE
