Metadata-Version: 2.4
Name: python-ottype
Version: 25.7.0
Summary: A python implementation of Operational Transformation.
Author: Jungkook Park
Author-email: pjknkda@gmail.com
License: MIT License
Project-URL: Homepage, https://github.com/pjknkda/python-ottype
Classifier: Development Status :: 5 - Production/Stable
Classifier: License :: OSI Approved :: MIT License
Classifier: Programming Language :: Python :: 3.9
Classifier: Programming Language :: Python :: 3.10
Classifier: Programming Language :: Python :: 3.11
Classifier: Programming Language :: Python :: 3.12
Classifier: Programming Language :: Python :: 3.13
Classifier: Programming Language :: Python :: Implementation :: CPython
Classifier: Operating System :: POSIX
Classifier: Operating System :: MacOS :: MacOS X
Requires-Python: <3.14,>=3.9
License-File: LICENSE
Provides-Extra: dev
Requires-Dist: bandit==1.8.6; extra == "dev"
Requires-Dist: black==25.1.0; extra == "dev"
Requires-Dist: Cython==3.1.2; extra == "dev"
Requires-Dist: flake8-bugbear==24.12.12; extra == "dev"
Requires-Dist: flake8-isort==6.1.2; extra == "dev"
Requires-Dist: flake8==7.3.0; extra == "dev"
Requires-Dist: mypy==1.16.1; extra == "dev"
Requires-Dist: pytest-cov==6.2.1; extra == "dev"
Requires-Dist: pytest==8.4.1; extra == "dev"
Requires-Dist: setuptools-scm==8.3.1; extra == "dev"
Dynamic: license-file
